[{"id":"15632","title":"A Book","imageUrl":"https://www.publicdomainpictures.net/pictures/10000/velka/1-1210009435EGmE.jpg","description":"This is an awesome book!","price":"19"},{"title":"sdsd","imageUrl":"","description":"dsf","price":"433","id":"0.6437256761638503"},{"title":"dsdf","imageUrl":"sdf","description":"wer","price":"4","id":"0.360064741704347"},{"title":"sds","imageUrl":"","description":"sd","price":"44","id":"0.8445760193696032"},{"title":"dfsf","imageUrl":"","description":"","price":"44","id":"0.193036771358579"},{"title":"ww","imageUrl":"","description":"","price":"","id":"0.889813502216195"},{"title":"sada","imageUrl":"","description":"","price":"","id":"0.3067179029602216"}]